wpimath/__init__.py
wpimath/py.typed
wpimath/units.py
wpimath/version.py
wpimath/_controls/__init__.py
wpimath/_controls/controls.cpp
wpimath/_impl/__init__.py
wpimath/_impl/src/PyTrajectoryConstraint.h
wpimath/_impl/src/type_casters/_units_base_type_caster.h
wpimath/_impl/src/type_casters/frc_eigen.h
wpimath/_impl/src/type_casters/units_acceleration_type_caster.h
wpimath/_impl/src/type_casters/units_angle_type_caster.h
wpimath/_impl/src/type_casters/units_angular_acceleration_type_caster.h
wpimath/_impl/src/type_casters/units_angular_velocity_type_caster.h
wpimath/_impl/src/type_casters/units_area_type_caster.h
wpimath/_impl/src/type_casters/units_capacitance_type_caster.h
wpimath/_impl/src/type_casters/units_charge_type_caster.h
wpimath/_impl/src/type_casters/units_compound_type_caster.h
wpimath/_impl/src/type_casters/units_concentration_type_caster.h
wpimath/_impl/src/type_casters/units_conductance_type_caster.h
wpimath/_impl/src/type_casters/units_current_type_caster.h
wpimath/_impl/src/type_casters/units_data_transfer_rate_type_caster.h
wpimath/_impl/src/type_casters/units_data_type_caster.h
wpimath/_impl/src/type_casters/units_density_type_caster.h
wpimath/_impl/src/type_casters/units_energy_type_caster.h
wpimath/_impl/src/type_casters/units_force_type_caster.h
wpimath/_impl/src/type_casters/units_frequency_type_caster.h
wpimath/_impl/src/type_casters/units_illuminance_type_caster.h
wpimath/_impl/src/type_casters/units_impedance_type_caster.h
wpimath/_impl/src/type_casters/units_inductance_type_caster.h
wpimath/_impl/src/type_casters/units_length_type_caster.h
wpimath/_impl/src/type_casters/units_luminous_flux_type_caster.h
wpimath/_impl/src/type_casters/units_luminous_intensity_type_caster.h
wpimath/_impl/src/type_casters/units_magnetic_field_strength_type_caster.h
wpimath/_impl/src/type_casters/units_magnetic_flux_type_caster.h
wpimath/_impl/src/type_casters/units_mass_type_caster.h
wpimath/_impl/src/type_casters/units_misc_type_caster.h
robotpy_wpimath-2025.3.2.3.dist-info/METADATA
robotpy_wpimath-2025.3.2.3.dist-info/WHEEL
robotpy_wpimath-2025.3.2.3.dist-info/entry_points.txt
robotpy_wpimath-2025.3.2.3.dist-info/RECORD
